limbo/__init__.py
limbo/fakeserver.py
limbo/limbo.py
limbo/server.py
limbo/slack.py
limbo/plugins/__init__.py
limbo/plugins/affirmation.py
limbo/plugins/banner.py
limbo/plugins/cat.py
limbo/plugins/commit.py
limbo/plugins/define.py
limbo/plugins/dog.py
limbo/plugins/emoji.py
limbo/plugins/emojicodedict.py
limbo/plugins/flip.py
limbo/plugins/gif.py
limbo/plugins/github.py
limbo/plugins/glossary.py
limbo/plugins/google.py
limbo/plugins/help.py
limbo/plugins/image.py
limbo/plugins/log.py
limbo/plugins/poll.py
limbo/plugins/taylor.py
limbo/plugins/weather.py
limbo/plugins/wiki.py
limbo-9.1.0.data/scripts/limbo
limbo-9.1.0.dist-info/LICENSE
limbo-9.1.0.dist-info/METADATA
limbo-9.1.0.dist-info/WHEEL
limbo-9.1.0.dist-info/top_level.txt
limbo-9.1.0.dist-info/RECORD
