Metadata-Version: 2.1
Name: limbo
Version: 9.1.0
Summary: Simple and Clean Slack Chatbot
Home-page: https://github.com/llimllib/limbo
Author: Bill Mill
Author-email: bill@billmill.org
License: MIT
Keywords: slack chatbot chat limbo
Classifier: Development Status :: 5 - Production/Stable
Classifier: Intended Audience :: Developers
Classifier: Natural Language :: English
Classifier: License :: OSI Approved :: MIT License
Classifier: Programming Language :: Python
Classifier: Programming Language :: Python :: 3.10
Classifier: Programming Language :: Python :: 3.12
Requires-Python: >=3.4
License-File: LICENSE
Requires-Dist: beautifulsoup4 ==4.12.3
Requires-Dist: certifi ==2024.2.2
Requires-Dist: charset-normalizer ==3.3.2
Requires-Dist: coverage ==7.4.3
Requires-Dist: flake8 ==7.0.0
Requires-Dist: html5lib ==1.1
Requires-Dist: idna ==3.6
Requires-Dist: iniconfig ==2.0.0
Requires-Dist: mccabe ==0.7.0
Requires-Dist: multidict ==6.0.5
Requires-Dist: packaging ==23.2
Requires-Dist: pluggy ==1.4.0
Requires-Dist: pycodestyle ==2.11.1
Requires-Dist: pyfiglet ==1.0.2
Requires-Dist: pyflakes ==3.2.0
Requires-Dist: pytest ==8.1.1
Requires-Dist: pytest-cov ==4.1.0
Requires-Dist: PyYAML ==6.0.1
Requires-Dist: requests ==2.31.0
Requires-Dist: setuptools ==69.1.1
Requires-Dist: six ==1.16.0
Requires-Dist: soupsieve ==2.5
Requires-Dist: urllib3 ==2.2.1
Requires-Dist: vcrpy ==6.0.1
Requires-Dist: webencodings ==0.5.1
Requires-Dist: websocket-client ==1.7.0
Requires-Dist: wrapt ==1.16.0
Requires-Dist: yarl ==1.9.4
